hdl/__init__.py
hdl/_version.py
hdl/args/__init__.py
hdl/args/loss_args.py
hdl/controllers/__init__.py
hdl/controllers/al/__init__.py
hdl/controllers/al/al.py
hdl/controllers/al/dispatcher.py
hdl/controllers/al/feedback.py
hdl/controllers/explain/__init__.py
hdl/controllers/explain/shapley.py
hdl/controllers/explain/subgraphx.py
hdl/controllers/train/__init__.py
hdl/controllers/train/rxn_train.py
hdl/controllers/train/train.py
hdl/controllers/train/train_ginet.py
hdl/controllers/train/trainer_base.py
hdl/controllers/train/trainer_iterative.py
hdl/data/__init__.py
hdl/data/to_mols.py
hdl/data/dataset/__init__.py
hdl/data/dataset/base_dataset.py
hdl/data/dataset/utils.py
hdl/data/dataset/fp/__init__.py
hdl/data/dataset/fp/fp_dataset.py
hdl/data/dataset/graph/__init__.py
hdl/data/dataset/graph/chiral.py
hdl/data/dataset/graph/gin.py
hdl/data/dataset/graph/molnet.py
hdl/data/dataset/loaders/__init__.py
hdl/data/dataset/loaders/chiral_graph.py
hdl/data/dataset/loaders/general.py
hdl/data/dataset/loaders/spliter.py
hdl/data/dataset/loaders/collate_funcs/__init__.py
hdl/data/dataset/loaders/collate_funcs/fp.py
hdl/data/dataset/loaders/collate_funcs/rxn.py
hdl/data/dataset/samplers/__init__.py
hdl/data/dataset/samplers/chiral.py
hdl/data/dataset/seq/__init__.py
hdl/data/dataset/seq/rxn_dataset.py
hdl/datasets/city_code.json
hdl/datasets/city_embs.npy
hdl/datasets/defined_BaseFeatures.fdef
hdl/datasets/las.tsv
hdl/datasets/route_template.json
hdl/datasets/vocab.txt
hdl/features/__init__.py
hdl/features/fp/__init__.py
hdl/features/fp/features_generators.py
hdl/features/graph/__init__.py
hdl/features/graph/featurization.py
hdl/features/utils/__init__.py
hdl/features/utils/utils.py
hdl/jupyfuncs/__init__.py
hdl/jupyfuncs/chem/__init__.py
hdl/jupyfuncs/chem/mol.py
hdl/jupyfuncs/chem/norm.py
hdl/jupyfuncs/chem/pdb_ext.py
hdl/jupyfuncs/chem/scaffold.py
hdl/jupyfuncs/chem/shape.py
hdl/jupyfuncs/chem/tokenizers.py
hdl/jupyfuncs/dbtools/__init__.py
hdl/jupyfuncs/dbtools/pg.py
hjxdl-0.3.59.dist-info/licenses/LICENSE
hjxdl-0.3.59.dist-info/METADATA
hjxdl-0.3.59.dist-info/WHEEL
hjxdl-0.3.59.dist-info/top_level.txt
hjxdl-0.3.59.dist-info/RECORD
